photonpy/__init__.py
photonpy/ui.py
photonpy/cpp/__init__.py
photonpy/cpp/calib.py
photonpy/cpp/com.py
photonpy/cpp/context.py
photonpy/cpp/cspline.py
photonpy/cpp/estim_queue.py
photonpy/cpp/estimator.py
photonpy/cpp/gaussian.py
photonpy/cpp/glrt.py
photonpy/cpp/image_proc.py
photonpy/cpp/lib.py
photonpy/cpp/phasor.py
photonpy/cpp/postprocess.py
photonpy/cpp/roi_queue.py
photonpy/cpp/simflux.py
photonpy/cpp/spotdetect.py
photonpy/examples/__init__.py
photonpy/examples/astigm_gauss2D_zstack.py
photonpy/examples/localize_3D.py
photonpy/examples/localize_spots.py
photonpy/examples/spot_detect_example.py
photonpy/gaussian/__init__.py
photonpy/gaussian/fitters.py
photonpy/simflux/__init__.py
photonpy/simflux/simflux.py
photonpy/simflux/spotlist.py
photonpy/smlm/__init__.py
photonpy/smlm/blinking_spots.py
photonpy/smlm/dataset.py
photonpy/smlm/drift_estimate.py
photonpy/smlm/extract_rois.py
photonpy/smlm/frc.py
photonpy/smlm/process_movie.py
photonpy/smlm/psf.py
photonpy/smlm/render.py
photonpy/smlm/util.py
photonpy/smlm/ui/__init__.py
photonpy/smlm/ui/app.py
photonpy/smlm/ui/drift_correct_dlg.py
photonpy/smlm/ui/drift_correct_ui.py
photonpy/smlm/ui/linklocs_ui.py
photonpy/smlm/ui/main_ui.py
photonpy/smlm/ui/progressbar.py
photonpy/smlm/ui/progressbar_ui.py
photonpy/smlm/ui/qtplot.py
photonpy/tests/__init__.py
photonpy/tests/crlb_g2d.py
photonpy/tests/dataset_pick.py
photonpy/tests/fft.py
photonpy/tests/fft2.py
photonpy/tests/gaussian3d_psf.py
photonpy/tests/glrt_psf.py
photonpy/tests/median_filter.py
photonpy/tests/phasor_crlb.py
photonpy/tests/phasor_simple.py
photonpy/tests/psf.py
photonpy/tests/psf_crlb.py
photonpy/tests/psf_g2d_sigma.py
photonpy/tests/psf_queue.py
photonpy/tests/simflux_g2d.py
photonpy/tests/simflux_psf.py
photonpy/utils/__init__.py
photonpy/utils/array.py
photonpy/utils/caching.py
photonpy/utils/dftpeak.py
photonpy/utils/draw_pointcloud_mean.py
photonpy/utils/findpeak1D.py
photonpy/utils/fitpoints2D.py
photonpy/utils/hdf5_density_filter.py
photonpy-1.0.39.dist-info/LICENSE.txt
photonpy-1.0.39.dist-info/METADATA
photonpy-1.0.39.dist-info/WHEEL
photonpy-1.0.39.dist-info/top_level.txt
photonpy-1.0.39.dist-info/RECORD
