Metadata-Version: 2.1
Name: photonpy
Version: 1.0.39
Summary: CUDA-Based image processing for single molecule localization microscopy
Home-page: https://github.com/qnano/photonpy
Author: Jelmer Cnossen
Author-email: j.p.cnossen@tudelft.nl
License: UNKNOWN
Platform: UNKNOWN
Classifier: Programming Language :: Python :: 3
Classifier: Programming Language :: C++
Classifier: License :: OSI Approved :: MIT License
Classifier: Operating System :: Microsoft :: Windows
Requires-Dist: scipy
Requires-Dist: numpy
Requires-Dist: matplotlib
Requires-Dist: tqdm
Requires-Dist: tifffile
Requires-Dist: h5py
Requires-Dist: pyyaml
Requires-Dist: scikit-image
Requires-Dist: pyqtgraph
